aliyun_oss_x-0.1.8.dist-info/METADATA
aliyun_oss_x-0.1.8.dist-info/WHEEL
aliyun_oss_x-0.1.8.dist-info/entry_points.txt
aliyun_oss_x-0.1.8.dist-info/licenses/LICENSE
aliyun_oss_x/__init__.py
aliyun_oss_x/__version__.py
aliyun_oss_x/api/__init__.py
aliyun_oss_x/api/_types.py
aliyun_oss_x/api/_utils.py
aliyun_oss_x/api/async_api.py
aliyun_oss_x/api/sync_api.py
aliyun_oss_x/auth.py
aliyun_oss_x/compat.py
aliyun_oss_x/crc64_combine.py
aliyun_oss_x/credentials.py
aliyun_oss_x/crypto.py
aliyun_oss_x/crypto_bucket/__init__.py
aliyun_oss_x/crypto_bucket/async_crypto_bucket.py
aliyun_oss_x/crypto_bucket/sync_crypto_bucket.py
aliyun_oss_x/defaults.py
aliyun_oss_x/exceptions.py
aliyun_oss_x/headers.py
aliyun_oss_x/http/__init__.py
aliyun_oss_x/iterators/__init__.py
aliyun_oss_x/iterators/async_iterators.py
aliyun_oss_x/iterators/sync_iterators.py
aliyun_oss_x/models.py
aliyun_oss_x/resumable/__init__.py
aliyun_oss_x/resumable/_base.py
aliyun_oss_x/resumable/async_resumable.py
aliyun_oss_x/resumable/sync_resumable.py
aliyun_oss_x/select_params.py
aliyun_oss_x/select_response.py
aliyun_oss_x/task_queue.py
aliyun_oss_x/types.py
aliyun_oss_x/utils/__init__.py
aliyun_oss_x/utils/adapter/async_adapter.py
aliyun_oss_x/utils/adapter/sync_adapter.py
aliyun_oss_x/utils/crc.py
aliyun_oss_x/xml_utils.py
aliyun_oss_x-0.1.8.dist-info/RECORD
