Metadata-Version: 2.1
Name: aliyun-oss-x
Version: 0.1.8
Summary: Aliyun OSS SDK for Python with async support
Author-Email: Anderson <andersonby@163.com>
License: MIT
Requires-Python: >=3.10
Requires-Dist: httpx[http2]>=0.28.0
Requires-Dist: pycryptodome>=3.21.0
Requires-Dist: crcmod>=1.7
Provides-Extra: aliyun-kms
Requires-Dist: aliyun-python-sdk-kms; extra == "aliyun-kms"
Requires-Dist: aliyun-python-sdk-core; extra == "aliyun-kms"
